hello_gh_actions/__init__.py
hello_gh_actions/fizzbuzz.py
hello_gh_actions/hello.py
hello_gh_actions-0.0.4.dist-info/AUTHORS
hello_gh_actions-0.0.4.dist-info/LICENSE
hello_gh_actions-0.0.4.dist-info/METADATA
hello_gh_actions-0.0.4.dist-info/WHEEL
hello_gh_actions-0.0.4.dist-info/pbr.json
hello_gh_actions-0.0.4.dist-info/top_level.txt
hello_gh_actions-0.0.4.dist-info/RECORD
